LICENSE
README.md
setup.py
gromorg/__init__.py
gromorg/cache.py
gromorg/capture.py
gromorg/data_structure.py
gromorg/setparam.py
gromorg/swisparam.py
gromorg/tools.py
gromorg/utils.py
gromorg.egg-info/PKG-INFO
gromorg.egg-info/SOURCES.txt
gromorg.egg-info/dependency_links.txt
gromorg.egg-info/requires.txt
gromorg.egg-info/top_level.txt