Metadata-Version: 1.1
Name: gromorg
Version: 0.2
Summary: Simple Gromacs python wrapper
Home-page: https://github.com/abelcarreras/gromorg
Author: Abel Carreras
Author-email: abelcarreras83@gmail.com
License: UNKNOWN
Platform: UNKNOWN
Classifier: Programming Language :: Python
Classifier: License :: OSI Approved :: MIT License
